MANIFEST.in
setup.py
larksuite_oapi.egg-info/PKG-INFO
larksuite_oapi.egg-info/SOURCES.txt
larksuite_oapi.egg-info/dependency_links.txt
larksuite_oapi.egg-info/requires.txt
larksuite_oapi.egg-info/top_level.txt
larksuiteoapi/__init__.py
larksuiteoapi/app_settings.py
larksuiteoapi/config.py
larksuiteoapi/consts.py
larksuiteoapi/context.py
larksuiteoapi/logger.py
larksuiteoapi/store.py
larksuiteoapi/api/__init__.py
larksuiteoapi/api/api_error.py
larksuiteoapi/api/tokens.py
larksuiteoapi/api/request/__init__.py
larksuiteoapi/api/request/form_data.py
larksuiteoapi/api/request/request.py
larksuiteoapi/api/response/__init__.py
larksuiteoapi/api/response/response.py
larksuiteoapi/card/__init__.py
larksuiteoapi/card/card.py
larksuiteoapi/card/handler/__init__.py
larksuiteoapi/card/handler/handlers.py
larksuiteoapi/card/handler/manager.py
larksuiteoapi/card/model/__init__.py
larksuiteoapi/card/model/card.py
larksuiteoapi/card/model/error.py
larksuiteoapi/event/__init__.py
larksuiteoapi/event/event.py
larksuiteoapi/event/app/__init__.py
larksuiteoapi/event/app/ticket.py
larksuiteoapi/event/handler/__init__.py
larksuiteoapi/event/handler/handlers.py
larksuiteoapi/event/handler/manager.py
larksuiteoapi/event/model/__init__.py
larksuiteoapi/event/model/error.py
larksuiteoapi/event/model/event.py
larksuiteoapi/model/__init__.py
larksuiteoapi/model/oapi_header.py
larksuiteoapi/model/oapi_request.py
larksuiteoapi/model/oapi_response.py
larksuiteoapi/service/__init__.py
larksuiteoapi/service/acs/__init__.py
larksuiteoapi/service/acs/v1/__init__.py
larksuiteoapi/service/acs/v1/api.py
larksuiteoapi/service/acs/v1/event.py
larksuiteoapi/service/acs/v1/model.py
larksuiteoapi/service/admin/__init__.py
larksuiteoapi/service/admin/v1/__init__.py
larksuiteoapi/service/admin/v1/api.py
larksuiteoapi/service/admin/v1/model.py
larksuiteoapi/service/application/__init__.py
larksuiteoapi/service/application/v1/__init__.py
larksuiteoapi/service/application/v1/event.py
larksuiteoapi/service/application/v1/model.py
larksuiteoapi/service/application/v6/__init__.py
larksuiteoapi/service/application/v6/api.py
larksuiteoapi/service/application/v6/event.py
